{
  "openapi": "3.0.1",
  "info": {
    "title": "Units OData Microservice",
    "description": "<div style='color:gray;font-weight:bold'>Build #: <span style='font-weight:bolder'>1.20.152.01</span></div>",
    "version": "1.0"
  },
  "paths": {
    "/odata/v1/Buildings": {
      "get": {
        "tags": [
          "Buildings"
        ],
        "parameters": [
          {
            "name": "$select",
            "in": "query",
            "description": "Limits the properties returned in the result.",
            "schema": {
              "type": "string"
            }
          },
          {
            "name": "$expand",
            "in": "query",
            "description": "Indicates the related entities to be represented inline. The maximum depth is 2.",
            "schema": {
              "type": "string"
            }
          }
        ],
        "responses": {
          "200": {
            "description": "Success",
            "content": {
              "application/json": {
                "schema": {
                  "$ref": "#/components/schemas/BuildingODataEnvelope"
                }
              }
            }
          }
        }
      }
    },
    "/odata/v1/SiteCollections": {
      "get": {
        "tags": [
          "SiteCollections"
        ],
        "parameters": [
          {
            "name": "tid",
            "in": "query",
            "schema": {
              "type": "string",
              "nullable": true
            }
          },
          {
            "name": "$select",
            "in": "query",
            "description": "Limits the properties returned in the result.",
            "schema": {
              "type": "string"
            }
          },
          {
            "name": "$expand",
            "in": "query",
            "description": "Indicates the related entities to be represented inline. The maximum depth is 2.",
            "schema": {
              "type": "string"
            }
          }
        ],
        "responses": {
          "200": {
            "description": "Success",
            "content": {
              "application/json": {
                "schema": {
                  "$ref": "#/components/schemas/SiteCollectionODataEnvelope"
                }
              }
            }
          }
        }
      }
    },
    "/odata/v1/Sites": {
      "get": {
        "tags": [
          "Sites"
        ],
        "parameters": [
          {
            "name": "tid",
            "in": "query",
            "schema": {
              "type": "string",
              "nullable": true
            }
          },
          {
            "name": "$select",
            "in": "query",
            "description": "Limits the properties returned in the result.",
            "schema": {
              "type": "string"
            }
          },
          {
            "name": "$expand",
            "in": "query",
            "description": "Indicates the related entities to be represented inline. The maximum depth is 2.",
            "schema": {
              "type": "string"
            }
          }
        ],
        "responses": {
          "200": {
            "description": "Success",
            "content": {
              "application/json": {
                "schema": {
                  "$ref": "#/components/schemas/SiteODataEnvelope"
                }
              }
            }
          }
        }
      }
    },
    "/odata/v1/Units": {
      "get": {
        "tags": [
          "Units"
        ],
        "parameters": [
          {
            "name": "$select",
            "in": "query",
            "description": "Limits the properties returned in the result.",
            "schema": {
              "type": "string"
            }
          },
          {
            "name": "$expand",
            "in": "query",
            "description": "Indicates the related entities to be represented inline. The maximum depth is 2.",
            "schema": {
              "type": "string"
            }
          }
        ],
        "responses": {
          "200": {
            "description": "Success",
            "content": {
              "application/json": {
                "schema": {
                  "$ref": "#/components/schemas/UnitODataEnvelope"
                }
              }
            }
          }
        }
      }
    },
    "/odata/v1/UnitTypes": {
      "get": {
        "tags": [
          "UnitTypes"
        ],
        "parameters": [
          {
            "name": "$select",
            "in": "query",
            "description": "Limits the properties returned in the result.",
            "schema": {
              "type": "string"
            }
          },
          {
            "name": "$expand",
            "in": "query",
            "description": "Indicates the related entities to be represented inline. The maximum depth is 2.",
            "schema": {
              "type": "string"
            }
          }
        ],
        "responses": {
          "200": {
            "description": "Success",
            "content": {
              "application/json": {
                "schema": {
                  "$ref": "#/components/schemas/UnitTypeODataEnvelope"
                }
              }
            }
          }
        }
      }
    }
  },
  "components": {
    "schemas": {
      "SiteCollection": {
        "required": [
          "code",
          "isSchedulerEnabled",
          "name",
          "number",
          "workCategoryTypes"
        ],
        "type": "object",
        "properties": {
          "id": {
            "type": "string",
            "format": "uuid"
          },
          "tenantId": {
            "type": "string",
            "nullable": true
          },
          "number": {
            "type": "string"
          },
          "name": {
            "type": "string"
          },
          "code": {
            "type": "string"
          },
          "addressLine1": {
            "type": "string",
            "nullable": true
          },
          "addressLine2": {
            "type": "string",
            "nullable": true
          },
          "city": {
            "type": "string",
            "nullable": true
          },
          "state": {
            "maxLength": 2,
            "minLength": 2,
            "type": "string",
            "nullable": true
          },
          "zip": {
            "maxLength": 10,
            "minLength": 5,
            "type": "string",
            "nullable": true
          },
          "isSchedulerEnabled": {
            "type": "boolean"
          },
          "siteCount": {
            "type": "integer",
            "format": "int32"
          },
          "workCategoryTypes": {
            "enum": [
              0,
              1,
              2,
              4,
              8,
              16,
              32,
              64,
              128
            ],
            "type": "integer",
            "format": "int32"
          },
          "buildings": {
            "type": "array",
            "items": {
              "$ref": "#/components/schemas/Building"
            },
            "nullable": true,
            "readOnly": true
          },
          "sites": {
            "type": "array",
            "items": {
              "$ref": "#/components/schemas/Site"
            },
            "nullable": true,
            "readOnly": true
          },
          "createdBy": {
            "type": "string",
            "nullable": true
          },
          "updatedBy": {
            "type": "string",
            "nullable": true
          },
          "createdOnUtc": {
            "type": "string",
            "format": "date-time"
          },
          "updatedOnUtc": {
            "type": "string",
            "format": "date-time",
            "nullable": true
          }
        },
        "additionalProperties": false
      },
      "UnitType": {
        "type": "object",
        "properties": {
          "id": {
            "type": "string",
            "format": "uuid"
          },
          "code": {
            "type": "string",
            "nullable": true
          },
          "description": {
            "type": "string",
            "nullable": true
          }
        },
        "additionalProperties": false
      },
      "Tag": {
        "type": "object",
        "properties": {
          "id": {
            "type": "string",
            "format": "uuid"
          },
          "name": {
            "type": "string",
            "nullable": true
          },
          "value": {
            "type": "string",
            "nullable": true
          },
          "unitTags": {
            "type": "array",
            "items": {
              "$ref": "#/components/schemas/UnitTag"
            },
            "nullable": true,
            "readOnly": true
          }
        },
        "additionalProperties": false
      },
      "UnitTag": {
        "type": "object",
        "properties": {
          "id": {
            "type": "string",
            "format": "uuid"
          },
          "unitId": {
            "type": "string",
            "format": "uuid"
          },
          "tagId": {
            "type": "string",
            "format": "uuid"
          },
          "value": {
            "type": "string",
            "nullable": true
          },
          "tag": {
            "$ref": "#/components/schemas/Tag"
          },
          "unit": {
            "$ref": "#/components/schemas/Unit"
          }
        },
        "additionalProperties": false
      },
      "Unit": {
        "type": "object",
        "properties": {
          "id": {
            "type": "string",
            "format": "uuid"
          },
          "number": {
            "type": "string",
            "nullable": true
          },
          "unitTypeId": {
            "type": "string",
            "format": "uuid"
          },
          "siteId": {
            "type": "string",
            "format": "uuid"
          },
          "buildingId": {
            "type": "string",
            "format": "uuid",
            "nullable": true
          },
          "isEnabled": {
            "type": "boolean"
          },
          "createdBy": {
            "type": "string",
            "nullable": true
          },
          "updatedBy": {
            "type": "string",
            "nullable": true
          },
          "createdOnUtc": {
            "type": "string",
            "format": "date-time"
          },
          "updatedOnUtc": {
            "type": "string",
            "format": "date-time",
            "nullable": true
          },
          "building": {
            "$ref": "#/components/schemas/Building"
          },
          "site": {
            "$ref": "#/components/schemas/Site"
          },
          "unitType": {
            "$ref": "#/components/schemas/UnitType"
          },
          "unitTags": {
            "type": "array",
            "items": {
              "$ref": "#/components/schemas/UnitTag"
            },
            "nullable": true,
            "readOnly": true
          }
        },
        "additionalProperties": false
      },
      "Site": {
        "type": "object",
        "properties": {
          "id": {
            "type": "string",
            "format": "uuid"
          },
          "tenantId": {
            "type": "string",
            "nullable": true
          },
          "accountId": {
            "type": "string",
            "format": "uuid"
          },
          "accountName": {
            "type": "string",
            "nullable": true
          },
          "siteCollectionId": {
            "type": "string",
            "format": "uuid"
          },
          "number": {
            "type": "string",
            "nullable": true
          },
          "name": {
            "type": "string",
            "nullable": true
          },
          "addressLine1": {
            "type": "string",
            "nullable": true
          },
          "addressLine2": {
            "type": "string",
            "nullable": true
          },
          "city": {
            "type": "string",
            "nullable": true
          },
          "state": {
            "type": "string",
            "nullable": true
          },
          "zip": {
            "type": "string",
            "nullable": true
          },
          "isEnabled": {
            "type": "boolean"
          },
          "createdBy": {
            "type": "string",
            "nullable": true
          },
          "updatedBy": {
            "type": "string",
            "nullable": true
          },
          "createdOnUtc": {
            "type": "string",
            "format": "date-time"
          },
          "updatedOnUtc": {
            "type": "string",
            "format": "date-time",
            "nullable": true
          },
          "siteCollection": {
            "$ref": "#/components/schemas/SiteCollection"
          },
          "buildings": {
            "type": "array",
            "items": {
              "$ref": "#/components/schemas/Building"
            },
            "nullable": true,
            "readOnly": true
          },
          "units": {
            "type": "array",
            "items": {
              "$ref": "#/components/schemas/Unit"
            },
            "nullable": true,
            "readOnly": true
          }
        },
        "additionalProperties": false
      },
      "Building": {
        "type": "object",
        "properties": {
          "id": {
            "type": "string",
            "format": "uuid"
          },
          "siteId": {
            "type": "string",
            "format": "uuid",
            "nullable": true
          },
          "identifier": {
            "type": "string",
            "nullable": true
          },
          "isEnabled": {
            "type": "boolean"
          },
          "createdBy": {
            "type": "string",
            "nullable": true
          },
          "updatedBy": {
            "type": "string",
            "nullable": true
          },
          "createdOnUtc": {
            "type": "string",
            "format": "date-time"
          },
          "updatedOnUtc": {
            "type": "string",
            "format": "date-time",
            "nullable": true
          },
          "site": {
            "$ref": "#/components/schemas/Site"
          },
          "units": {
            "type": "array",
            "items": {
              "$ref": "#/components/schemas/Unit"
            },
            "nullable": true,
            "readOnly": true
          }
        },
        "additionalProperties": false
      },
      "BuildingODataEnvelope": {
        "type": "object",
        "properties": {
          "value": {
            "type": "array",
            "items": {
              "$ref": "#/components/schemas/Building"
            },
            "nullable": true
          },
          "count": {
            "type": "integer",
            "format": "int32",
            "nullable": true
          }
        },
        "additionalProperties": false
      },
      "SiteCollectionODataEnvelope": {
        "type": "object",
        "properties": {
          "value": {
            "type": "array",
            "items": {
              "$ref": "#/components/schemas/SiteCollection"
            },
            "nullable": true
          },
          "count": {
            "type": "integer",
            "format": "int32",
            "nullable": true
          }
        },
        "additionalProperties": false
      },
      "SiteODataEnvelope": {
        "type": "object",
        "properties": {
          "value": {
            "type": "array",
            "items": {
              "$ref": "#/components/schemas/Site"
            },
            "nullable": true
          },
          "count": {
            "type": "integer",
            "format": "int32",
            "nullable": true
          }
        },
        "additionalProperties": false
      },
      "UnitODataEnvelope": {
        "type": "object",
        "properties": {
          "value": {
            "type": "array",
            "items": {
              "$ref": "#/components/schemas/Unit"
            },
            "nullable": true
          },
          "count": {
            "type": "integer",
            "format": "int32",
            "nullable": true
          }
        },
        "additionalProperties": false
      },
      "UnitTypeODataEnvelope": {
        "type": "object",
        "properties": {
          "value": {
            "type": "array",
            "items": {
              "$ref": "#/components/schemas/UnitType"
            },
            "nullable": true
          },
          "count": {
            "type": "integer",
            "format": "int32",
            "nullable": true
          }
        },
        "additionalProperties": false
      }
    },
    "securitySchemes": {
      "Bearer": {
        "type": "oauth2",
        "description": "JWT Authorization header using the Bearer scheme. Example: \"Authorization: Bearer {token}\"",
        "flows": {
          "implicit": {
            "authorizationUrl": "https://mastercorp-d.auth0.com/authorize?audience=Units-D",
            "scopes": {
              "openid": "required"
            }
          }
        }
      }
    }
  },
  "security": [
    {
      "Bearer": [ ]
    }
  ]
}